aspine/__init__.py
aspine/cli.py
aspine/core/__init__.py
aspine/core/async_mp_bridge.py
aspine/core/cache_storage.py
aspine/core/client.py
aspine/core/server.py
aspine-2.0.0.dist-info/LICENSE
aspine-2.0.0.dist-info/METADATA
aspine-2.0.0.dist-info/WHEEL
aspine-2.0.0.dist-info/entry_points.txt
aspine-2.0.0.dist-info/top_level.txt
aspine-2.0.0.dist-info/RECORD
